O365/__init__.py
O365/account.py
O365/address_book.py
O365/calendar.py
O365/category.py
O365/connection.py
O365/directory.py
O365/directory.py~
O365/drive.py
O365/excel.py
O365/groups.py
O365/mailbox.py
O365/message.py
O365/planner.py
O365/sharepoint.py
O365/subscriptions.py
O365/tasks.py
O365/teams.py
O365/utils/__init__.py
O365/utils/attachment.py
O365/utils/casing.py
O365/utils/consent.py
O365/utils/decorators.py
O365/utils/query.py
O365/utils/range.py
O365/utils/token.py
O365/utils/utils.py
O365/utils/windows_tz.py
o365-2.1.9.dist-info/WHEEL
o365-2.1.9.dist-info/METADATA
o365-2.1.9.dist-info/RECORD
