Metadata-Version: 2.3
Name: o365
Version: 2.1.9
Summary: O365 - Microsoft Graph and Office 365 API made easy
Author: Alejcas, Narcolapser, Roycem90
Author-email: Alejcas <alejcas@users.noreply.github.com>, Narcolapser <narcolapser@users.noreply.github.com>, Roycem90 <roycem90@users.noreply.github.com>
Classifier: Development Status :: 5 - Production/Stable
Classifier: Intended Audience :: Developers
Classifier: License :: OSI Approved :: Apache Software License
Classifier: Programming Language :: Python :: 3.10
Classifier: Programming Language :: Python :: 3.11
Classifier: Programming Language :: Python :: 3.12
Classifier: Programming Language :: Python :: 3.13
Classifier: Operating System :: OS Independent
Requires-Dist: beautifulsoup4>=4.12.3
Requires-Dist: msal>=1.31.1
Requires-Dist: python-dateutil>=2.9.0.post0
Requires-Dist: requests>=2.32.3
Requires-Dist: tzdata>=2024.2
Requires-Dist: tzlocal>=5.2
Maintainer: Alejcas
Maintainer-email: Alejcas <alejcas@users.noreply.github.com>
Requires-Python: >=3.10
